pipeline_runtime/__init__.py
pipeline_runtime-1.0.11.dist-info/METADATA
pipeline_runtime-1.0.11.dist-info/RECORD
pipeline_runtime-1.0.11.dist-info/WHEEL
pipeline_runtime-1.0.11.dist-info/top_level.txt
