Metadata-Version: 2.1
Name: pipeline-runtime
Version: 1.0.11
Summary: PipelineAI Runtime
Home-page: https://github.com/PipelineAI/
Author: Chris Fregly
Author-email: github@pipeline.ai
License: UNKNOWN
Platform: UNKNOWN
Requires-Dist: pipeline-logger (==1.0.2)
Requires-Dist: pipeline-monitor (==1.0.1)
Requires-Dist: pipeline-model (==1.0.10)
Requires-Dist: cloudpickle (>=0.3.1)
